{"00": "attAwcixXG9JY9aiz", "01": "attH5qjp0rbSkQvuV", "02": "attCyvk4DcmnzbEpE", "03": "attD8el1XfAS43bc3", "04": "att4Z1TzYBpMpNQui", "05": "attsFJwLlT3wpJ2KX", "06": "atthpshA7LGvSXhJ4", "07": "attRNwmiEGZx5zm5v", "08": "attStWKUI0ILmBTDw", "09": "attlRZAfIjTlcptDV", "10": "attpd9kzTYgFZeGzB", "11": "attskDX33h3sc8Rs8", "12": "att9mqOnskOhrZex6", "13": "attiUFT4meBP6nXWb", "14": "attSX9V7pQlkbTvSy", "15": "attq1QCK6XHjeWbzG", "16": "atttr7YhfXzsgbp9j", "17": "atteLH4BPd8Uz7h3j", "18": "attBbovPOUXRKLT3G", "19": "attZak8DB0yTYDH1m", "20": "attYSxCcfQZnuMiN5", "21": "attuF5Jgw39ZU8MqX", "22": "attcaEkmAdYb14dKY", "23": "attQAFy2JrJ7qH2qa"}